<?xml version="1.0" encoding="UTF-8"?>
<?xml-model href="span.rng" type="application/xml" schematypens="http://relaxng.org/ns/structure/1.0"?>

<layer xmlns="http://ids-mannheim.de/ns/KorAP" docid="BZK_D59.00089" version="KorAP-0.4">
   <spanList>
      <span id="s1_n4" from="0" to="14"/>
      <span id="s1_n6" from="15" to="19"/>
      <span id="s1_n9" from="20" to="23"/>
      <span id="s1_n13" from="24" to="27"/>
      <span id="s1_n15" from="28" to="29"/>
      <span id="s1_n20" from="29" to="32"/>
      <span id="s1_n22" from="32" to="33"/>
      <span id="s1_n25" from="34" to="37"/>
      <span id="s1_n29" from="38" to="41"/>
      <span id="s1_n31" from="42" to="45"/>
      <span id="s1_n33" from="46" to="63"/>
      <span id="s1_n36" from="64" to="71"/>
      <span id="s1_n38" from="72" to="75"/>
      <span id="s1_n40" from="76" to="80"/>
      <span id="s1_n42" from="81" to="100"/>
      <span id="s1_n44" from="101" to="107"/>
      <span id="s1_n46" from="108" to="116"/>
      <span id="s1_n48" from="117" to="118"/>
      <span id="s1_n51" from="119" to="122"/>
      <span id="s1_n54" from="123" to="128"/>
      <span id="s1_n56" from="129" to="133"/>
      <span id="s1_n58" from="134" to="145"/>
      <span id="s1_n60" from="145" to="146"/>
      <span id="s1_n63" from="147" to="154"/>
      <span id="s1_n66" from="155" to="158"/>
      <span id="s1_n68" from="159" to="166"/>
      <span id="s1_n70" from="167" to="171"/>
      <span id="s1_n73" from="172" to="179"/>
      <span id="s1_n75" from="180" to="190"/>
      <span id="s1_n77" from="191" to="201"/>
      <span id="s1_n80" from="202" to="207"/>
      <span id="s1_n82" from="208" to="216"/>
      <span id="s1_n84" from="217" to="221"/>
      <span id="s1_n86" from="222" to="224"/>
      <span id="s1_n88" from="225" to="228"/>
      <span id="s1_n92" from="229" to="234"/>
      <span id="s1_n94" from="235" to="238"/>
      <span id="s1_n96" from="239" to="244"/>
      <span id="s1_n99" from="245" to="246"/>
      <span id="s1_n101" from="246" to="262"/>
      <span id="s1_n104" from="263" to="266"/>
      <span id="s1_n106" from="267" to="282"/>
      <span id="s1_n108" from="283" to="293"/>
      <span id="s1_n110" from="293" to="294"/>
      <span id="s1_n114" from="295" to="299"/>
      <span id="s1_n116" from="300" to="304"/>
      <span id="s1_n118" from="305" to="315"/>
      <span id="s1_n120" from="316" to="327"/>
      <span id="s1_n124" from="328" to="331"/>
      <span id="s1_n126" from="332" to="337"/>
      <span id="s1_n128" from="338" to="345"/>
      <span id="s1_n130" from="346" to="352"/>
      <span id="s1_n132" from="352" to="353"/>
      <span id="s2_n4" from="354" to="369"/>
      <span id="s2_n6" from="370" to="377"/>
      <span id="s2_n8" from="378" to="383"/>
      <span id="s2_n10" from="384" to="388"/>
      <span id="s2_n13" from="389" to="391"/>
      <span id="s2_n15" from="392" to="395"/>
      <span id="s2_n17" from="396" to="403"/>
      <span id="s2_n19" from="404" to="409"/>
      <span id="s2_n22" from="410" to="414"/>
      <span id="s2_n24" from="415" to="436"/>
      <span id="s2_n27" from="437" to="440"/>
      <span id="s2_n29" from="441" to="461"/>
      <span id="s2_n31" from="462" to="468"/>
      <span id="s2_n34" from="469" to="472"/>
      <span id="s2_n36" from="473" to="474"/>
      <span id="s2_n38" from="474" to="490"/>
      <span id="s2_n40" from="490" to="491"/>
      <span id="s2_n43" from="492" to="505"/>
      <span id="s2_n45" from="505" to="506"/>
      <span id="s3_n4" from="507" to="509"/>
      <span id="s3_n6" from="510" to="515"/>
      <span id="s3_n8" from="516" to="519"/>
      <span id="s3_n10" from="520" to="523"/>
      <span id="s3_n13" from="524" to="527"/>
      <span id="s3_n15" from="528" to="540"/>
      <span id="s3_n18" from="541" to="544"/>
      <span id="s3_n21" from="545" to="551"/>
      <span id="s3_n23" from="551" to="552"/>
      <span id="s3_n25" from="553" to="558"/>
      <span id="s3_n27" from="559" to="562"/>
      <span id="s3_n29" from="563" to="569"/>
      <span id="s3_n31" from="569" to="570"/>
      <span id="s4_n4" from="571" to="574"/>
      <span id="s4_n6" from="575" to="596"/>
      <span id="s4_n9" from="597" to="604"/>
      <span id="s4_n11" from="604" to="605"/>
      <span id="s4_n13" from="606" to="613"/>
      <span id="s4_n15" from="614" to="617"/>
      <span id="s4_n17" from="618" to="625"/>
      <span id="s4_n19" from="626" to="637"/>
      <span id="s4_n22" from="638" to="641"/>
      <span id="s4_n25" from="643" to="647"/>
      <span id="s4_n27" from="648" to="657"/>
      <span id="s4_n29" from="658" to="666"/>
      <span id="s4_n32" from="667" to="670"/>
      <span id="s4_n34" from="671" to="679"/>
      <span id="s4_n37" from="680" to="683"/>
      <span id="s4_n39" from="684" to="687"/>
      <span id="s4_n41" from="688" to="702"/>
      <span id="s4_n43" from="702" to="703"/>
      <span id="s5_n4" from="704" to="707"/>
      <span id="s5_n6" from="708" to="711"/>
      <span id="s5_n8" from="712" to="714"/>
      <span id="s5_n10" from="715" to="735"/>
      <span id="s5_n13" from="736" to="739"/>
      <span id="s5_n15" from="740" to="760"/>
      <span id="s5_n17" from="761" to="767"/>
      <span id="s5_n19" from="768" to="773"/>
      <span id="s5_n21" from="774" to="778"/>
      <span id="s5_n24" from="779" to="789"/>
      <span id="s5_n26" from="790" to="792"/>
      <span id="s5_n29" from="793" to="796"/>
      <span id="s5_n31" from="797" to="802"/>
      <span id="s5_n33" from="803" to="804"/>
      <span id="s5_n35" from="804" to="820"/>
      <span id="s5_n37" from="820" to="821"/>
      <span id="s5_n40" from="822" to="835"/>
      <span id="s5_n42" from="835" to="836"/>
   </spanList>
</layer>
