<?xml version="1.0" encoding="UTF-8"?>
<?xml-model href="span.rng" type="application/xml" schematypens="http://relaxng.org/ns/structure/1.0"?>

<layer docid="CMC-TSK_2014-09.3401" xmlns="http://ids-mannheim.de/ns/KorAP" version="KorAP-0.4">
  <spanList>
    <span id="s1" from="15" to="15">
      <fs type="lex" xmlns="http://www.tei-c.org/ns/1.0">
        <f name="lex">
          <fs>
            <f name="lemma">Naja</f>
          </fs>
        </f>
      </fs>
    </span>
    <span id="s2" from="17" to="18">
      <fs type="lex" xmlns="http://www.tei-c.org/ns/1.0">
        <f name="lex">
          <fs>
            <f name="lemma">Na</f>
          </fs>
        </f>
      </fs>
    </span>
    <span id="s3" from="19" to="21">
      <fs type="lex" xmlns="http://www.tei-c.org/ns/1.0">
        <f name="lex">
          <fs>
            <f name="lemma">ja</f>
          </fs>
        </f>
      </fs>
    </span>
    <span id="s4" from="22" to="26">
      <fs type="lex" xmlns="http://www.tei-c.org/ns/1.0">
        <f name="lex">
          <fs>
            <f name="lemma">wenn</f>
          </fs>
        </f>
      </fs>
    </span>
    <span id="s5" from="27" to="30">
      <fs type="lex" xmlns="http://www.tei-c.org/ns/1.0">
        <f name="lex">
          <fs>
            <f name="lemma">Sie</f>
          </fs>
        </f>
      </fs>
    </span>
    <span id="s6" from="31" to="36">
      <fs type="lex" xmlns="http://www.tei-c.org/ns/1.0">
        <f name="lex">
          <fs>
            <f name="lemma">Nazi</f>
          </fs>
        </f>
      </fs>
    </span>
    <span id="s7" from="37" to="40">
      <fs type="lex" xmlns="http://www.tei-c.org/ns/1.0">
        <f name="lex">
          <fs>
            <f name="lemma">nur</f>
          </fs>
        </f>
      </fs>
    </span>
    <span id="s8" from="41" to="43">
      <fs type="lex" xmlns="http://www.tei-c.org/ns/1.0">
        <f name="lex">
          <fs>
            <f name="lemma">an</f>
          </fs>
        </f>
      </fs>
    </span>
    <span id="s9" from="44" to="49">
      <fs type="lex" xmlns="http://www.tei-c.org/ns/1.0">
        <f name="lex">
          <fs>
            <f name="lemma">Deren</f>
          </fs>
        </f>
      </fs>
    </span>
    <span id="s10" from="50" to="63">
      <fs type="lex" xmlns="http://www.tei-c.org/ns/1.0">
        <f name="lex">
          <fs>
            <f name="lemma">Kennzeichnung</f>
          </fs>
        </f>
      </fs>
    </span>
    <span id="s11" from="64" to="73">
      <fs type="lex" xmlns="http://www.tei-c.org/ns/1.0">
        <f name="lex">
          <fs>
            <f name="lemma">ausmachen</f>
          </fs>
        </f>
      </fs>
    </span>
    <span id="s12" from="86" to="89">
      <fs type="lex" xmlns="http://www.tei-c.org/ns/1.0">
        <f name="lex">
          <fs>
            <f name="lemma">Sie</f>
          </fs>
        </f>
      </fs>
    </span>
    <span id="s13" from="90" to="94">
      <fs type="lex" xmlns="http://www.tei-c.org/ns/1.0">
        <f name="lex">
          <fs>
            <f name="lemma">aber</f>
          </fs>
        </f>
      </fs>
    </span>
    <span id="s14" from="95" to="97">
      <fs type="lex" xmlns="http://www.tei-c.org/ns/1.0">
        <f name="lex">
          <fs>
            <f name="lemma">im</f>
            <f name="lemma">in</f>
            <f name="lemma">in.</f>
          </fs>
        </f>
      </fs>
    </span>
    <span id="s15" from="98" to="106">
      <fs type="lex" xmlns="http://www.tei-c.org/ns/1.0">
        <f name="lex">
          <fs>
            <f name="lemma">falsch</f>
          </fs>
        </f>
      </fs>
    </span>
    <span id="s16" from="107" to="113">
      <fs type="lex" xmlns="http://www.tei-c.org/ns/1.0">
        <f name="lex">
          <fs>
            <f name="lemma">Weiher</f>
          </fs>
        </f>
      </fs>
    </span>
  </spanList>
</layer>